lab2.v
// pipelined fast multiplier
// pipelined fast multiplier
module mult_fast(
	output reg[7:0] P,  // product
	input[3:0] A, B,    // multiplicand and multiplier
	input clk		    // clock (posedge)
	);
	// stage 0 (input)
	reg[3:0] a_s0, b_s0;
	always @(posedge clk) begin
		a_s0 <= A;
		b_s0 <= B;
	end
	// stage 1
	wire[3:0] pp0 = a_s0 & {4{b_s0[0]}}; // ignore the delays of AND gates
	wire[4:1] pp1 = a_s0 & {4{b_s0[1]}}; // ignore the delays of AND gates
	wire[5:2] pp2 = a_s0 & {4{b_s0[2]}}; // ignore the delays of AND gates
	wire[6:3] pp3 = a_s0 & {4{b_s0[3]}}; // ignore the delays of AND gates
	reg[5:1] sum1;
	always @(pp0, pp1)
		sum1[5:1] <= #7 pp0[3:1] + pp1[4:1]; // delay of the 4-bit adder
	reg[7:3] sum3;
	always @(pp2, pp3)
		sum3[7:3] <= #7 pp2[5:3] + pp3[6:3]; // delay of the 4-bit adder
	reg[5:0] sum1_s1;
	reg[7:2] sum3_s1;
	always @(posedge clk) begin
		sum1_s1 <= {sum1, pp0[0]};
		sum3_s1 <= {sum3, pp2[2]};
	end
	// stage 2 (outout)
	reg[7:2] sum2;
	always @(sum1_s1, sum3_s1)
		sum2[7:2] <= #8 sum1_s1[5:2] + sum3_s1[7:2]; // delay of the 6-bit adder
	always @(posedge clk) begin
		P <= {sum2, sum1_s1[1:0]};
	end
endmodule

// test bench
module mult_tb();
	// dump
	initial begin
		$dumpfile("lab2.vcd");
		$dumpvars(0, mult_tb);
	end
	// clock cycle = 10 ticks
	reg clock = 1;
	always
		#3.5 clock <= ~clock;
	// multiplier
	reg[3:0] A, B;
	wire[7:0] P;
	reg[7:0] P_ref;
	mult_fast mult(P, A, B, clock);
	always @(posedge clock)
		P_ref <= #14 A*B;
	// loop through all possible inputs
	integer i;
	initial begin
		#9;
		for(i=0; i<256; i=i+1) begin
			{A, B} <= i;
			#10;
		end
		#21 $finish;
	end
	// check if the products are correct
	reg[3:0] A_old, B_old;
	always @(posedge clock) begin
		#1
		if(P_ref!=P && i>=2) begin
			A_old = (i-2)/16;
			B_old = (i-2)%16;
			$display("Product is wrong when A=%b, B=%b.", A_old, B_old);
			$display("P_ref: %b.", P_ref);
			$display("P    : %b.", P);
			#9 $finish;
		end
	end
endmodule

lab2.vcd
$date
	Sat May 18 23:38:26 2024
$end
$version
	Icarus Verilog
$end
$timescale
	1s
$end
$scope module mult_tb $end
$var wire 8 ! P [7:0] $end
$var reg 4 " A [3:0] $end
$var reg 4 # A_old [3:0] $end
$var reg 4 $ B [3:0] $end
$var reg 4 % B_old [3:0] $end
$var reg 8 & P_ref [7:0] $end
$var reg 1 ' clock $end
$var integer 32 ( i [31:0] $end
$scope module mult $end
$var wire 4 ) A [3:0] $end
$var wire 4 * B [3:0] $end
$var wire 1 + clk $end
$var wire 4 , pp0 [3:0] $end
$var wire 4 - pp1 [4:1] $end
$var wire 4 . pp2 [5:2] $end
$var wire 4 / pp3 [6:3] $end
$var reg 8 0 P [7:0] $end
$var reg 4 1 a_s0 [3:0] $end
$var reg 4 2 b_s0 [3:0] $end
$var reg 5 3 sum1 [5:1] $end
$var reg 6 4 sum1_s1 [5:0] $end
$var reg 6 5 sum2 [7:2] $end
$var reg 5 6 sum3 [7:3] $end
$var reg 6 7 sum3_s1 [7:2] $end
$upscope $end
$upscope $end
$enddefinitions $end
#0
$dumpvars
bx 7
bx 6
bx 5
bx 4
bx 3
bx 2
bx 1
bx 0
bx /
bx .
bx -
bx ,
1+
bx *
bx )
bx (
1'
bx &
bx %
bx $
bx #
bx "
bx !
$end
#4
0'
0+
#8
1'
1+
#9
b0 "
b0 )
b0 $
b0 *
b0 (
#12
0'
0+
#16
b0 /
b0 .
b0 -
b0 ,
b0 2
b0 1
1'
1+
#19
b1 $
b1 *
b1 (
#20
0'
0+
#23
b0 6
b0 3
#24
b0 7
b0 4
b1 2
1'
1+
#28
0'
0+
#29
b10 $
b10 *
b10 (
#30
b0 &
#32
b10 2
b0 0
b0 !
1'
1+
b0 5
#36
0'
0+
#39
b11 $
b11 *
b11 (
#40
b11 2
1'
1+
#44
0'
0+
#48
1'
1+
#49
b100 $
b100 *
b100 (
#52
0'
0+
#56
b100 2
1'
1+
#59
b101 $
b101 *
b101 (
#60
0'
0+
#64
b101 2
1'
1+
#68
0'
0+
#69
b110 $
b110 *
b110 (
#72
b110 2
1'
1+
#76
0'
0+
#79
b111 $
b111 *
b111 (
#80
b111 2
1'
1+
#84
0'
0+
#88
1'
1+
#89
b1000 $
b1000 *
b1000 (
#92
0'
0+
#96
b1000 2
1'
1+
#99
b1001 $
b1001 *
b1001 (
#100
0'
0+
#104
b1001 2
1'
1+
#108
0'
0+
#109
b1010 $
b1010 *
b1010 (
#112
b1010 2
1'
1+
#116
0'
0+
#119
b1011 $
b1011 *
b1011 (
#120
b1011 2
1'
1+
#124
0'
0+
#128
1'
1+
#129
b1100 $
b1100 *
b1100 (
#132
0'
0+
#136
b1100 2
1'
1+
#139
b1101 $
b1101 *
b1101 (
#140
0'
0+
#144
b1101 2
1'
1+
#148
0'
0+
#149
b1110 $
b1110 *
b1110 (
#152
b1110 2
1'
1+
#156
0'
0+
#159
b1111 $
b1111 *
b1111 (
#160
b1111 2
1'
1+
#164
0'
0+
#168
1'
1+
#169
b1 "
b1 )
b0 $
b0 *
b10000 (
#172
0'
0+
#176
b0 /
b0 .
b0 -
b0 ,
b0 2
b1 1
1'
1+
#179
b1 $
b1 *
b10001 (
#180
0'
0+
#183
b0 6
b0 3
#184
b1 ,
b1 2
1'
1+
#188
0'
0+
#189
b10 $
b10 *
b10010 (
#192
b0 ,
b1 -
b10 2
b1 4
1'
1+
#196
0'
0+
#198
b1 &
#199
b11 $
b11 *
b1 3
b10011 (
#200
b1 ,
b1 0
b1 !
b10 4
b11 2
1'
1+
#204
0'
0+
#206
b10 &
#208
b11 4
b10 0
b10 !
1'
1+
#209
b100 $
b100 *
b10100 (
#212
0'
0+
#214
b11 &
#216
b0 ,
b0 -
b1 .
b11 0
b11 !
b100 2
1'
1+
#219
b101 $
b101 *
b10101 (
#220
0'
0+
#223
b0 3
#224
b1 ,
b101 2
b1 7
b0 4
1'
1+
#228
0'
0+
#229
b110 $
b110 *
b10110 (
#230
b100 &
#232
b0 ,
b1 -
b100 0
b100 !
b1 4
b110 2
1'
1+
b1 5
#236
0'
0+
#238
b101 &
#239
b111 $
b111 *
b1 3
b10111 (
#240
b1 ,
b111 2
b10 4
b101 0
b101 !
1'
1+
#244
0'
0+
#246
b110 &
#248
b110 0
b110 !
b11 4
1'
1+
#249
b1000 $
b1000 *
b11000 (
#252
0'
0+
#254
b111 &
#256
b0 ,
b0 -
b0 .
b1 /
b1000 2
b111 0
b111 !
1'
1+
#259
b1001 $
b1001 *
b11001 (
#260
0'
0+
#263
b0 3
b1 6
#264
b1 ,
b10 7
b0 4
b1001 2
1'
1+
#268
0'
0+
#269
b1010 $
b1010 *
b11010 (
#270
b1000 &
#272
b0 ,
b1 -
b1010 2
b1 4
b1000 0
b1000 !
1'
1+
b10 5
#276
0'
0+
#278
b1001 &
#279
b1011 $
b1011 *
b1 3
b11011 (
#280
b1 ,
b1001 0
b1001 !
b10 4
b1011 2
1'
1+
#284
0'
0+
#286
b1010 &
#288
b11 4
b1010 0
b1010 !
1'
1+
#289
b1100 $
b1100 *
b11100 (
#292
0'
0+
#294
b1011 &
#296
b0 ,
b0 -
b1 .
b1011 0
b1011 !
b1100 2
1'
1+
#299
b1101 $
b1101 *
b11101 (
#300
0'
0+
#303
b0 3
#304
b1 ,
b1101 2
b11 7
b0 4
1'
1+
#308
0'
0+
#309
b1110 $
b1110 *
b11110 (
#310
b1100 &
#312
b0 ,
b1 -
b1100 0
b1100 !
b1 4
b1110 2
1'
1+
b11 5
#316
0'
0+
#318
b1101 &
#319
b1111 $
b1111 *
b1 3
b11111 (
#320
b1 ,
b1111 2
b10 4
b1101 0
b1101 !
1'
1+
#324
0'
0+
#326
b1110 &
#328
b1110 0
b1110 !
b11 4
1'
1+
#329
b10 "
b10 )
b0 $
b0 *
b100000 (
#332
0'
0+
#334
b1111 &
#336
b0 /
b0 .
b0 -
b0 ,
b0 2
b10 1
b1111 0
b1111 !
1'
1+
#339
b1 $
b1 *
b100001 (
#340
0'
0+
#343
b0 6
b0 3
#344
b10 ,
b0 7
b0 4
b1 2
1'
1+
#348
0'
0+
#349
b10 $
b10 *
b100010 (
#350
b0 &
#351
b1 3
#352
b0 ,
b10 -
b10 2
b10 4
b0 0
b0 !
1'
1+
b0 5
#356
0'
0+
#358
b10 &
#359
b11 $
b11 *
b10 3
b100011 (
#360
b10 ,
b10 0
b10 !
b100 4
b11 2
1'
1+
#364
0'
0+
#366
b100 &
#367
b11 3
#368
b110 4
b100 0
b100 !
1'
1+
b1 5
#369
b100 $
b100 *
b100100 (
#372
0'
0+
#374
b110 &
#376
b0 ,
b0 -
b10 .
b110 0
b110 !
b100 2
1'
1+
#379
b101 $
b101 *
b100101 (
#380
0'
0+
#383
b0 3
b1 6
#384
b10 ,
b101 2
b10 7
b0 4
1'
1+
#388
0'
0+
#389
b110 $
b110 *
b100110 (
#390
b1000 &
#391
b1 3
#392
b0 ,
b10 -
b1000 0
b1000 !
b10 4
b110 2
1'
1+
b10 5
#396
0'
0+
#398
b1010 &
#399
b111 $
b111 *
b10 3
b100111 (
#400
b10 ,
b111 2
b100 4
b1010 0
b1010 !
1'
1+
#404
0'
0+
#406
b1100 &
#407
b11 3
#408
b1100 0
b1100 !
b110 4
1'
1+
b11 5
#409
b1000 $
b1000 *
b101000 (
#412
0'
0+
#414
b1110 &
#416
b0 ,
b0 -
b0 .
b10 /
b1000 2
b1110 0
b1110 !
1'
1+
#419
b1001 $
b1001 *
b101001 (
#420
0'
0+
#423
b0 3
b10 6
#424
b10 ,
b100 7
b0 4
b1001 2
1'
1+
#428
0'
0+
#429
b1010 $
b1010 *
b101010 (
#430
b10000 &
#431
b1 3
#432
b0 ,
b10 -
b1010 2
b10 4
b10000 0
b10000 !
1'
1+
b100 5
#436
0'
0+
#438
b10010 &
#439
b1011 $
b1011 *
b10 3
b101011 (
#440
b10 ,
b10010 0
b10010 !
b100 4
b1011 2
1'
1+
#444
0'
0+
#446
b10100 &
#447
b11 3
#448
b110 4
b10100 0
b10100 !
1'
1+
b101 5
#449
b1100 $
b1100 *
b101100 (
#452
0'
0+
#454
b10110 &
#456
b0 ,
b0 -
b10 .
b10110 0
b10110 !
b1100 2
1'
1+
#459
b1101 $
b1101 *
b101101 (
#460
0'
0+
#463
b0 3
b11 6
#464
b10 ,
b1101 2
b110 7
b0 4
1'
1+
#468
0'
0+
#469
b1110 $
b1110 *
b101110 (
#470
b11000 &
#471
b1 3
#472
b0 ,
b10 -
b11000 0
b11000 !
b10 4
b1110 2
1'
1+
b110 5
#476
0'
0+
#478
b11010 &
#479
b1111 $
b1111 *
b10 3
b101111 (
#480
b10 ,
b1111 2
b100 4
b11010 0
b11010 !
1'
1+
#484
0'
0+
#486
b11100 &
#487
b11 3
#488
b11100 0
b11100 !
b110 4
1'
1+
b111 5
#489
b11 "
b11 )
b0 $
b0 *
b110000 (
#492
0'
0+
#494
b11110 &
#496
b0 /
b0 .
b0 -
b0 ,
b0 2
b11 1
b11110 0
b11110 !
1'
1+
#499
b1 $
b1 *
b110001 (
#500
0'
0+
#503
b0 6
b0 3
#504
b11 ,
b0 7
b0 4
b1 2
1'
1+
#508
0'
0+
#509
b10 $
b10 *
b110010 (
#510
b0 &
#511
b1 3
#512
b0 ,
b11 -
b10 2
b11 4
b0 0
b0 !
1'
1+
b0 5
#516
0'
0+
#518
b11 &
#519
b11 $
b11 *
b11 3
b110011 (
#520
b11 ,
b11 0
b11 !
b110 4
b11 2
1'
1+
#524
0'
0+
#526
b110 &
#527
b100 3
#528
b1001 4
b110 0
b110 !
1'
1+
b1 5
#529
b100 $
b100 *
b110100 (
#532
0'
0+
#534
b1001 &
#536
b0 ,
b0 -
b11 .
b1001 0
b1001 !
b100 2
1'
1+
b10 5
#539
b101 $
b101 *
b110101 (
#540
0'
0+
#543
b0 3
b1 6
#544
b11 ,
b101 2
b11 7
b0 4
1'
1+
#548
0'
0+
#549
b110 $
b110 *
b110110 (
#550
b1100 &
#551
b1 3
#552
b0 ,
b11 -
b1100 0
b1100 !
b11 4
b110 2
1'
1+
b11 5
#556
0'
0+
#558
b1111 &
#559
b111 $
b111 *
b11 3
b110111 (
#560
b11 ,
b111 2
b110 4
b1111 0
b1111 !
1'
1+
#564
0'
0+
#566
b10010 &
#567
b100 3
#568
b10010 0
b10010 !
b1001 4
1'
1+
b100 5
#569
b1000 $
b1000 *
b111000 (
#572
0'
0+
#574
b10101 &
#576
b0 ,
b0 -
b0 .
b11 /
b1000 2
b10101 0
b10101 !
1'
1+
b101 5
#579
b1001 $
b1001 *
b111001 (
#580
0'
0+
#583
b0 3
b11 6
#584
b11 ,
b110 7
b0 4
b1001 2
1'
1+
#588
0'
0+
#589
b1010 $
b1010 *
b111010 (
#590
b11000 &
#591
b1 3
#592
b0 ,
b11 -
b1010 2
b11 4
b11000 0
b11000 !
1'
1+
b110 5
#596
0'
0+
#598
b11011 &
#599
b1011 $
b1011 *
b11 3
b111011 (
#600
b11 ,
b11011 0
b11011 !
b110 4
b1011 2
1'
1+
#604
0'
0+
#606
b11110 &
#607
b100 3
#608
b1001 4
b11110 0
b11110 !
1'
1+
b111 5
#609
b1100 $
b1100 *
b111100 (
#612
0'
0+
#614
b100001 &
#616
b0 ,
b0 -
b11 .
b100001 0
b100001 !
b1100 2
1'
1+
b1000 5
#619
b1101 $
b1101 *
b111101 (
#620
0'
0+
#623
b0 3
b100 6
#624
b11 ,
b1101 2
b1001 7
b0 4
1'
1+
#628
0'
0+
#629
b1110 $
b1110 *
b111110 (
#630
b100100 &
#631
b1 3
#632
b0 ,
b11 -
b100100 0
b100100 !
b11 4
b1110 2
1'
1+
b1001 5
#636
0'
0+
#638
b100111 &
#639
b1111 $
b1111 *
b11 3
b111111 (
#640
b11 ,
b1111 2
b110 4
b100111 0
b100111 !
1'
1+
#644
0'
0+
#646
b101010 &
#647
b100 3
#648
b101010 0
b101010 !
b1001 4
1'
1+
b1010 5
#649
b100 "
b100 )
b0 $
b0 *
b1000000 (
#652
0'
0+
#654
b101101 &
#656
b0 /
b0 .
b0 -
b0 ,
b0 2
b100 1
b101101 0
b101101 !
1'
1+
b1011 5
#659
b1 $
b1 *
b1000001 (
#660
0'
0+
#663
b0 6
b0 3
#664
b100 ,
b0 7
b0 4
b1 2
1'
1+
#668
0'
0+
#669
b10 $
b10 *
b1000010 (
#670
b0 &
#671
b10 3
#672
b0 ,
b100 -
b10 2
b100 4
b0 0
b0 !
1'
1+
b0 5
#676
0'
0+
#678
b100 &
#679
b11 $
b11 *
b100 3
b1000011 (
#680
b100 ,
b100 0
b100 !
b1000 4
b11 2
1'
1+
b1 5
#684
0'
0+
#686
b1000 &
#687
b110 3
#688
b1100 4
b1000 0
b1000 !
1'
1+
b10 5
#689
b100 $
b100 *
b1000100 (
#692
0'
0+
#694
b1100 &
#696
b0 ,
b0 -
b100 .
b1100 0
b1100 !
b100 2
1'
1+
b11 5
#699
b101 $
b101 *
b1000101 (
#700
0'
0+
#703
b0 3
b10 6
#704
b100 ,
b101 2
b100 7
b0 4
1'
1+
#708
0'
0+
#709
b110 $
b110 *
b1000110 (
#710
b10000 &
#711
b10 3
#712
b0 ,
b100 -
b10000 0
b10000 !
b100 4
b110 2
1'
1+
b100 5
#716
0'
0+
#718
b10100 &
#719
b111 $
b111 *
b100 3
b1000111 (
#720
b100 ,
b111 2
b1000 4
b10100 0
b10100 !
1'
1+
b101 5
#724
0'
0+
#726
b11000 &
#727
b110 3
#728
b11000 0
b11000 !
b1100 4
1'
1+
b110 5
#729
b1000 $
b1000 *
b1001000 (
#732
0'
0+
#734
b11100 &
#736
b0 ,
b0 -
b0 .
b100 /
b1000 2
b11100 0
b11100 !
1'
1+
b111 5
#739
b1001 $
b1001 *
b1001001 (
#740
0'
0+
#743
b0 3
b100 6
#744
b100 ,
b1000 7
b0 4
b1001 2
1'
1+
#748
0'
0+
#749
b1010 $
b1010 *
b1001010 (
#750
b100000 &
#751
b10 3
#752
b0 ,
b100 -
b1010 2
b100 4
b100000 0
b100000 !
1'
1+
b1000 5
#756
0'
0+
#758
b100100 &
#759
b1011 $
b1011 *
b100 3
b1001011 (
#760
b100 ,
b100100 0
b100100 !
b1000 4
b1011 2
1'
1+
b1001 5
#764
0'
0+
#766
b101000 &
#767
b110 3
#768
b1100 4
b101000 0
b101000 !
1'
1+
b1010 5
#769
b1100 $
b1100 *
b1001100 (
#772
0'
0+
#774
b101100 &
#776
b0 ,
b0 -
b100 .
b101100 0
b101100 !
b1100 2
1'
1+
b1011 5
#779
b1101 $
b1101 *
b1001101 (
#780
0'
0+
#783
b0 3
b110 6
#784
b100 ,
b1101 2
b1100 7
b0 4
1'
1+
#788
0'
0+
#789
b1110 $
b1110 *
b1001110 (
#790
b110000 &
#791
b10 3
#792
b0 ,
b100 -
b110000 0
b110000 !
b100 4
b1110 2
1'
1+
b1100 5
#796
0'
0+
#798
b110100 &
#799
b1111 $
b1111 *
b100 3
b1001111 (
#800
b100 ,
b1111 2
b1000 4
b110100 0
b110100 !
1'
1+
b1101 5
#804
0'
0+
#806
b111000 &
#807
b110 3
#808
b111000 0
b111000 !
b1100 4
1'
1+
b1110 5
#809
b101 "
b101 )
b0 $
b0 *
b1010000 (
#812
0'
0+
#814
b111100 &
#816
b0 /
b0 .
b0 -
b0 ,
b0 2
b101 1
b111100 0
b111100 !
1'
1+
b1111 5
#819
b1 $
b1 *
b1010001 (
#820
0'
0+
#823
b0 6
b0 3
#824
b101 ,
b0 7
b0 4
b1 2
1'
1+
#828
0'
0+
#829
b10 $
b10 *
b1010010 (
#830
b0 &
#831
b10 3
#832
b0 ,
b101 -
b10 2
b101 4
b0 0
b0 !
1'
1+
b0 5
#836
0'
0+
#838
b101 &
#839
b11 $
b11 *
b101 3
b1010011 (
#840
b101 ,
b101 0
b101 !
b1010 4
b11 2
1'
1+
b1 5
#844
0'
0+
#846
b1010 &
#847
b111 3
#848
b1111 4
b1010 0
b1010 !
1'
1+
b10 5
#849
b100 $
b100 *
b1010100 (
#852
0'
0+
#854
b1111 &
#856
b0 ,
b0 -
b101 .
b1111 0
b1111 !
b100 2
1'
1+
b11 5
#859
b101 $
b101 *
b1010101 (
#860
0'
0+
#863
b0 3
b10 6
#864
b101 ,
b101 2
b101 7
b0 4
1'
1+
#868
0'
0+
#869
b110 $
b110 *
b1010110 (
#870
b10100 &
#871
b10 3
#872
b0 ,
b101 -
b10100 0
b10100 !
b101 4
b110 2
1'
1+
b101 5
#876
0'
0+
#878
b11001 &
#879
b111 $
b111 *
b101 3
b1010111 (
#880
b101 ,
b111 2
b1010 4
b11001 0
b11001 !
1'
1+
b110 5
#884
0'
0+
#886
b11110 &
#887
b111 3
#888
b11110 0
b11110 !
b1111 4
1'
1+
b111 5
#889
b1000 $
b1000 *
b1011000 (
#892
0'
0+
#894
b100011 &
#896
b0 ,
b0 -
b0 .
b101 /
b1000 2
b100011 0
b100011 !
1'
1+
b1000 5
#899
b1001 $
b1001 *
b1011001 (
#900
0'
0+
#903
b0 3
b101 6
#904
b101 ,
b1010 7
b0 4
b1001 2
1'
1+
#908
0'
0+
#909
b1010 $
b1010 *
b1011010 (
#910
b101000 &
#911
b10 3
#912
b0 ,
b101 -
b1010 2
b101 4
b101000 0
b101000 !
1'
1+
b1010 5
#916
0'
0+
#918
b101101 &
#919
b1011 $
b1011 *
b101 3
b1011011 (
#920
b101 ,
b101101 0
b101101 !
b1010 4
b1011 2
1'
1+
b1011 5
#924
0'
0+
#926
b110010 &
#927
b111 3
#928
b1111 4
b110010 0
b110010 !
1'
1+
b1100 5
#929
b1100 $
b1100 *
b1011100 (
#932
0'
0+
#934
b110111 &
#936
b0 ,
b0 -
b101 .
b110111 0
b110111 !
b1100 2
1'
1+
b1101 5
#939
b1101 $
b1101 *
b1011101 (
#940
0'
0+
#943
b0 3
b111 6
#944
b101 ,
b1101 2
b1111 7
b0 4
1'
1+
#948
0'
0+
#949
b1110 $
b1110 *
b1011110 (
#950
b111100 &
#951
b10 3
#952
b0 ,
b101 -
b111100 0
b111100 !
b101 4
b1110 2
1'
1+
b1111 5
#956
0'
0+
#958
b1000001 &
#959
b1111 $
b1111 *
b101 3
b1011111 (
#960
b101 ,
b1111 2
b1010 4
b1000001 0
b1000001 !
1'
1+
b10000 5
#964
0'
0+
#966
b1000110 &
#967
b111 3
#968
b1000110 0
b1000110 !
b1111 4
1'
1+
b10001 5
#969
b110 "
b110 )
b0 $
b0 *
b1100000 (
#972
0'
0+
#974
b1001011 &
#976
b0 /
b0 .
b0 -
b0 ,
b0 2
b110 1
b1001011 0
b1001011 !
1'
1+
b10010 5
#979
b1 $
b1 *
b1100001 (
#980
0'
0+
#983
b0 6
b0 3
#984
b110 ,
b0 7
b0 4
b1 2
1'
1+
#988
0'
0+
#989
b10 $
b10 *
b1100010 (
#990
b0 &
#991
b11 3
#992
b0 ,
b110 -
b10 2
b110 4
b0 0
b0 !
1'
1+
b0 5
#996
0'
0+
#998
b110 &
#999
b11 $
b11 *
b110 3
b1100011 (
#1000
b110 ,
b110 0
b110 !
b1100 4
b11 2
1'
1+
b1 5
#1004
0'
0+
#1006
b1100 &
#1007
b1001 3
#1008
b10010 4
b1100 0
b1100 !
1'
1+
b11 5
#1009
b100 $
b100 *
b1100100 (
#1012
0'
0+
#1014
b10010 &
#1016
b0 ,
b0 -
b110 .
b10010 0
b10010 !
b100 2
1'
1+
b100 5
#1019
b101 $
b101 *
b1100101 (
#1020
0'
0+
#1023
b0 3
b11 6
#1024
b110 ,
b101 2
b110 7
b0 4
1'
1+
#1028
0'
0+
#1029
b110 $
b110 *
b1100110 (
#1030
b11000 &
#1031
b11 3
#1032
b0 ,
b110 -
b11000 0
b11000 !
b110 4
b110 2
1'
1+
b110 5
#1036
0'
0+
#1038
b11110 &
#1039
b111 $
b111 *
b110 3
b1100111 (
#1040
b110 ,
b111 2
b1100 4
b11110 0
b11110 !
1'
1+
b111 5
#1044
0'
0+
#1046
b100100 &
#1047
b1001 3
#1048
b100100 0
b100100 !
b10010 4
1'
1+
b1001 5
#1049
b1000 $
b1000 *
b1101000 (
#1052
0'
0+
#1054
b101010 &
#1056
b0 ,
b0 -
b0 .
b110 /
b1000 2
b101010 0
b101010 !
1'
1+
b1010 5
#1059
b1001 $
b1001 *
b1101001 (
#1060
0'
0+
#1063
b0 3
b110 6
#1064
b110 ,
b1100 7
b0 4
b1001 2
1'
1+
#1068
0'
0+
#1069
b1010 $
b1010 *
b1101010 (
#1070
b110000 &
#1071
b11 3
#1072
b0 ,
b110 -
b1010 2
b110 4
b110000 0
b110000 !
1'
1+
b1100 5
#1076
0'
0+
#1078
b110110 &
#1079
b1011 $
b1011 *
b110 3
b1101011 (
#1080
b110 ,
b110110 0
b110110 !
b1100 4
b1011 2
1'
1+
b1101 5
#1084
0'
0+
#1086
b111100 &
#1087
b1001 3
#1088
b10010 4
b111100 0
b111100 !
1'
1+
b1111 5
#1089
b1100 $
b1100 *
b1101100 (
#1092
0'
0+
#1094
b1000010 &
#1096
b0 ,
b0 -
b110 .
b1000010 0
b1000010 !
b1100 2
1'
1+
b10000 5
#1099
b1101 $
b1101 *
b1101101 (
#1100
0'
0+
#1103
b0 3
b1001 6
#1104
b110 ,
b1101 2
b10010 7
b0 4
1'
1+
#1108
0'
0+
#1109
b1110 $
b1110 *
b1101110 (
#1110
b1001000 &
#1111
b11 3
#1112
b0 ,
b110 -
b1001000 0
b1001000 !
b110 4
b1110 2
1'
1+
b10010 5
#1116
0'
0+
#1118
b1001110 &
#1119
b1111 $
b1111 *
b110 3
b1101111 (
#1120
b110 ,
b1111 2
b1100 4
b1001110 0
b1001110 !
1'
1+
b10011 5
#1124
0'
0+
#1126
b1010100 &
#1127
b1001 3
#1128
b1010100 0
b1010100 !
b10010 4
1'
1+
b10101 5
#1129
b111 "
b111 )
b0 $
b0 *
b1110000 (
#1132
0'
0+
#1134
b1011010 &
#1136
b0 /
b0 .
b0 -
b0 ,
b0 2
b111 1
b1011010 0
b1011010 !
1'
1+
b10110 5
#1139
b1 $
b1 *
b1110001 (
#1140
0'
0+
#1143
b0 6
b0 3
#1144
b111 ,
b0 7
b0 4
b1 2
1'
1+
#1148
0'
0+
#1149
b10 $
b10 *
b1110010 (
#1150
b0 &
#1151
b11 3
#1152
b0 ,
b111 -
b10 2
b111 4
b0 0
b0 !
1'
1+
b0 5
#1156
0'
0+
#1158
b111 &
#1159
b11 $
b11 *
b111 3
b1110011 (
#1160
b111 ,
b111 0
b111 !
b1110 4
b11 2
1'
1+
b1 5
#1164
0'
0+
#1166
b1110 &
#1167
b1010 3
#1168
b10101 4
b1110 0
b1110 !
1'
1+
b11 5
#1169
b100 $
b100 *
b1110100 (
#1172
0'
0+
#1174
b10101 &
#1176
b0 ,
b0 -
b111 .
b10101 0
b10101 !
b100 2
1'
1+
b101 5
#1179
b101 $
b101 *
b1110101 (
#1180
0'
0+
#1183
b0 3
b11 6
#1184
b111 ,
b101 2
b111 7
b0 4
1'
1+
#1188
0'
0+
#1189
b110 $
b110 *
b1110110 (
#1190
b11100 &
#1191
b11 3
#1192
b0 ,
b111 -
b11100 0
b11100 !
b111 4
b110 2
1'
1+
b111 5
#1196
0'
0+
#1198
b100011 &
#1199
b111 $
b111 *
b111 3
b1110111 (
#1200
b111 ,
b111 2
b1110 4
b100011 0
b100011 !
1'
1+
b1000 5
#1204
0'
0+
#1206
b101010 &
#1207
b1010 3
#1208
b101010 0
b101010 !
b10101 4
1'
1+
b1010 5
#1209
b1000 $
b1000 *
b1111000 (
#1212
0'
0+
#1214
b110001 &
#1216
b0 ,
b0 -
b0 .
b111 /
b1000 2
b110001 0
b110001 !
1'
1+
b1100 5
#1219
b1001 $
b1001 *
b1111001 (
#1220
0'
0+
#1223
b0 3
b111 6
#1224
b111 ,
b1110 7
b0 4
b1001 2
1'
1+
#1228
0'
0+
#1229
b1010 $
b1010 *
b1111010 (
#1230
b111000 &
#1231
b11 3
#1232
b0 ,
b111 -
b1010 2
b111 4
b111000 0
b111000 !
1'
1+
b1110 5
#1236
0'
0+
#1238
b111111 &
#1239
b1011 $
b1011 *
b111 3
b1111011 (
#1240
b111 ,
b111111 0
b111111 !
b1110 4
b1011 2
1'
1+
b1111 5
#1244
0'
0+
#1246
b1000110 &
#1247
b1010 3
#1248
b10101 4
b1000110 0
b1000110 !
1'
1+
b10001 5
#1249
b1100 $
b1100 *
b1111100 (
#1252
0'
0+
#1254
b1001101 &
#1256
b0 ,
b0 -
b111 .
b1001101 0
b1001101 !
b1100 2
1'
1+
b10011 5
#1259
b1101 $
b1101 *
b1111101 (
#1260
0'
0+
#1263
b0 3
b1010 6
#1264
b111 ,
b1101 2
b10101 7
b0 4
1'
1+
#1268
0'
0+
#1269
b1110 $
b1110 *
b1111110 (
#1270
b1010100 &
#1271
b11 3
#1272
b0 ,
b111 -
b1010100 0
b1010100 !
b111 4
b1110 2
1'
1+
b10101 5
#1276
0'
0+
#1278
b1011011 &
#1279
b1111 $
b1111 *
b111 3
b1111111 (
#1280
b111 ,
b1111 2
b1110 4
b1011011 0
b1011011 !
1'
1+
b10110 5
#1284
0'
0+
#1286
b1100010 &
#1287
b1010 3
#1288
b1100010 0
b1100010 !
b10101 4
1'
1+
b11000 5
#1289
b1000 "
b1000 )
b0 $
b0 *
b10000000 (
#1292
0'
0+
#1294
b1101001 &
#1296
b0 /
b0 .
b0 -
b0 ,
b0 2
b1000 1
b1101001 0
b1101001 !
1'
1+
b11010 5
#1299
b1 $
b1 *
b10000001 (
#1300
0'
0+
#1303
b0 6
b0 3
#1304
b1000 ,
b0 7
b0 4
b1 2
1'
1+
#1308
0'
0+
#1309
b10 $
b10 *
b10000010 (
#1310
b0 &
#1311
b100 3
#1312
b0 ,
b1000 -
b10 2
b1000 4
b0 0
b0 !
1'
1+
b0 5
#1316
0'
0+
#1318
b1000 &
#1319
b11 $
b11 *
b1000 3
b10000011 (
#1320
b1000 ,
b1000 0
b1000 !
b10000 4
b11 2
1'
1+
b10 5
#1324
0'
0+
#1326
b10000 &
#1327
b1100 3
#1328
b11000 4
b10000 0
b10000 !
1'
1+
b100 5
#1329
b100 $
b100 *
b10000100 (
#1332
0'
0+
#1334
b11000 &
#1336
b0 ,
b0 -
b1000 .
b11000 0
b11000 !
b100 2
1'
1+
b110 5
#1339
b101 $
b101 *
b10000101 (
#1340
0'
0+
#1343
b0 3
b100 6
#1344
b1000 ,
b101 2
b1000 7
b0 4
1'
1+
#1348
0'
0+
#1349
b110 $
b110 *
b10000110 (
#1350
b100000 &
#1351
b100 3
#1352
b0 ,
b1000 -
b100000 0
b100000 !
b1000 4
b110 2
1'
1+
b1000 5
#1356
0'
0+
#1358
b101000 &
#1359
b111 $
b111 *
b1000 3
b10000111 (
#1360
b1000 ,
b111 2
b10000 4
b101000 0
b101000 !
1'
1+
b1010 5
#1364
0'
0+
#1366
b110000 &
#1367
b1100 3
#1368
b110000 0
b110000 !
b11000 4
1'
1+
b1100 5
#1369
b1000 $
b1000 *
b10001000 (
#1372
0'
0+
#1374
b111000 &
#1376
b0 ,
b0 -
b0 .
b1000 /
b1000 2
b111000 0
b111000 !
1'
1+
b1110 5
#1379
b1001 $
b1001 *
b10001001 (
#1380
0'
0+
#1383
b0 3
b1000 6
#1384
b1000 ,
b10000 7
b0 4
b1001 2
1'
1+
#1388
0'
0+
